tokhelper/__init__.py
tokhelper/captchaCheck_pb2.py
tokhelper/solve_captcha.py
tokhelper/tiktok_main.py
tokhelper/utils.py
tokive-1.7.data/scripts/tokive
tokive-1.7.dist-info/METADATA
tokive-1.7.dist-info/WHEEL
tokive-1.7.dist-info/top_level.txt
tokive-1.7.dist-info/RECORD
