Metadata-Version: 2.1
Name: tokive
Version: 1.7
Summary: A Des of tokive
Home-page: https://github.com/AutoWinTeam/tokive
Author: Thanh Hoa
Author-email: thanhhoakhmt1@gmail.com
Classifier: Programming Language :: Python :: 3
Classifier: License :: OSI Approved :: MIT License
Classifier: Operating System :: OS Independent
Requires-Dist: cryptography
Requires-Dist: requests
Requires-Dist: opencv-python
Requires-Dist: protobuf
Requires-Dist: numpy
